{"1314": {"PreClose": 11.1, "PreHigh": 11.1, "PreLow": 10.35}, "2305": {"PreClose": 32.2, "PreHigh": 32.2, "PreLow": 29.5}, "2405": {"PreClose": 15.95, "PreHigh": 15.95, "PreLow": 14.7}, "2702": {"PreClose": 25.6, "PreHigh": 26.05, "PreLow": 24.0}, "3701": {"PreClose": 52.7, "PreHigh": 52.7, "PreLow": 48.55}, "5258": {"PreClose": 72.0, "PreHigh": 72.0, "PreLow": 66.0}, "3207": {"PreClose": 45.25, "PreHigh": 45.25, "PreLow": 42.4}, "3434": {"PreClose": 34.3, "PreHigh": 34.3, "PreLow": 32.8}, "3466": {"PreClose": 29.1, "PreHigh": 29.25, "PreLow": 26.4}, "4162": {"PreClose": 127.0, "PreHigh": 127.0, "PreLow": 113.0}, "4167": {"PreClose": 18.95, "PreHigh": 18.95, "PreLow": 17.0}, "4726": {"PreClose": 45.75, "PreHigh": 45.75, "PreLow": 41.3}, "4743": {"PreClose": 242.5, "PreHigh": 242.5, "PreLow": 232.5}, "6185": {"PreClose": 14.4, "PreHigh": 14.4, "PreLow": 13.5}, "6589": {"PreClose": 111.5, "PreHigh": 111.5, "PreLow": 102.0}, "8933": {"PreClose": 14.45, "PreHigh": 14.45, "PreLow": 13.9}, "6550": {"PreClose": 164.0, "PreHigh": 165.0, "PreLow": 149.0}}